<?xml version="1.0" encoding="utf-8" ?>
<dwsync>
<file name="Function.php" server="oldbk.org" local="130064981280000000" remote="130301687400000000" Dst="0" />
<file name="Method.php" server="oldbk.org" local="130064981280000000" remote="130301687400000000" Dst="0" />
<file name="Node.php" server="oldbk.org" local="130064981280000000" remote="130301687400000000" Dst="0" />
<file name="Function.php" server="91.228.154.216" local="130064981280000000" remote="130555706400000000" Dst="0" />
<file name="Method.php" server="91.228.154.216" local="130064981280000000" remote="130555706400000000" Dst="0" />
<file name="Node.php" server="91.228.154.216" local="130064981280000000" remote="130555706400000000" Dst="0" />
<file name="Function.php" server="worldofcombats.ru" local="130064981280000000" remote="130568186400000000" Dst="2" />
<file name="Method.php" server="worldofcombats.ru" local="130064981280000000" remote="130568186400000000" Dst="2" />
<file name="Node.php" server="worldofcombats.ru" local="130064981280000000" remote="130568186400000000" Dst="2" />
<file name="Function.php" server="5.187.7.121" local="130064981280000000" remote="130764952200000000" Dst="0" />
<file name="Method.php" server="5.187.7.121" local="130064981280000000" remote="130764952200000000" Dst="0" />
<file name="Node.php" server="5.187.7.121" local="130064981280000000" remote="130764952200000000" Dst="0" />
<file name="Function.php" server="91.228.152.236" local="130064981280000000" remote="130772881800000000" Dst="0" />
<file name="Method.php" server="91.228.152.236" local="130064981280000000" remote="130772881800000000" Dst="0" />
<file name="Node.php" server="91.228.152.236" local="130064981280000000" remote="130772881800000000" Dst="0" />
<file name="Function.php" server="xn--80ab0aijvg.com" local="130064981280000000" remote="130912995000000000" Dst="0" />
<file name="Method.php" server="xn--80ab0aijvg.com" local="130064981280000000" remote="130912995000000000" Dst="0" />
<file name="Node.php" server="xn--80ab0aijvg.com" local="130064981280000000" remote="130912995000000000" Dst="0" />
<file name="Function.php" server="legbk.net" local="130064981280000000" remote="130913559000000000" Dst="0" />
<file name="Method.php" server="legbk.net" local="130064981280000000" remote="130913559000000000" Dst="0" />
<file name="Node.php" server="legbk.net" local="130064981280000000" remote="130913559000000000" Dst="0" />
<file name="Method.php" server="bk2.ru" local="130064981280000000" remote="130996533600000000" Dst="0" />
<file name="Function.php" server="bk2.ru" local="130064981280000000" remote="130996533600000000" Dst="0" />
<file name="Node.php" server="bk2.ru" local="130064981280000000" remote="130996533600000000" Dst="0" />
<file name="Function.php" server="xcombats.com" local="130064981280000000" remote="131278269600000000" Dst="0" />
<file name="Method.php" server="xcombats.com" local="130064981280000000" remote="131278269600000000" Dst="0" />
<file name="Node.php" server="xcombats.com" local="130064981280000000" remote="131278269600000000" Dst="0" />
<file name="Function.php" server="5.187.2.201" local="130064981280000000" remote="131286267000000000" Dst="0" />
<file name="Method.php" server="5.187.2.201" local="130064981280000000" remote="131286267000000000" Dst="0" />
<file name="Node.php" server="5.187.2.201" local="130064981280000000" remote="131286267000000000" Dst="0" />
</dwsync>