<?xml version="1.0" encoding="utf-8" ?>
<dwsync>
<file name="index.php" server="5.187.7.121" local="130765077285050214" remote="130764969000000000" Dst="0" />
<file name="index.php" server="91.228.152.236" local="130765077285050214" remote="130772881800000000" Dst="0" />
<file name="index.php" server="originalcombats.com" local="130889408348825455" remote="130889299800000000" Dst="0" />
<file name=".htaccess" server="xn--80ab0aijvg.com" local="130765060555077490" remote="130912995000000000" Dst="0" />
<file name="index.php" server="xn--80ab0aijvg.com" local="130913101220363373" remote="130912995000000000" Dst="0" />
<file name=".htaccess" server="legbk.net" local="130765060555077490" remote="130913559000000000" Dst="0" />
<file name="index.php" server="legbk.net" local="130956180703157847" remote="130956072600000000" Dst="0" />
<file name="index.php" server="bk2.ru" local="131015529374007941" remote="131015421600000000" Dst="0" />
<file name="index.php" server="5.187.7.71" local="131021068171451955" remote="131020959600000000" Dst="0" />
<file name="index.php" server="anticombats.com" local="131160616619788687" remote="131160508200000000" Dst="0" />
<file name="index.php" server="xcombats.com" local="131280022239798960" remote="131279914200000000" Dst="0" />
<file name="index.php" server="5.187.2.201" local="131339492211983736" remote="131339383800000000" Dst="0" />
<file name=".htaccess" server="5.187.2.201" local="130996763929781753" remote="131286266400000000" Dst="0" />
</dwsync>